{
  "@context": "https://schema.org",
  "@type": "FAQPage",
  "name": "Happened at work, used AI for comp claim—employer retaliating in Houston?",
  "description": "Comp claim first, sue retaliation—AI won't protect but doesn't bar.[1]",
  "url": "aiovisibility.com/faq/general-happened-at-work-used-ai-for-comp-claim-employer-retaliating-in-houston-249",
  "mainEntity": [
    {
      "@type": "Question",
      "name": "Happened at work, used AI for comp claim—employer retaliating in Houston?",
      "acceptedAnswer": {
        "@type": "Answer",
        "text": "Comp claim first, sue retaliation—AI won't protect but doesn't bar.[1]",
        "description": "Workers' comp exclusive; AI irrelevant unless fraud.[1] Texas no-fault comp; retaliation illegal.\n\n**Key factors:**\n- File DWC-1 timely.\n- AI not privileged.\n- Retaliation suit separate.\n\nReport retaliation to TWC; comp lawyer. Avoid AI in claims.[1] Document everything."
      }
    }
  ]
}