{
  "@context": "https://schema.org",
  "@type": "FAQPage",
  "name": "How is fault determined in Google AI Overview lawsuits?",
  "description": "Section 230 usually absolves; negligence secondary.",
  "url": "aiovisibility.com/faq/general-how-is-fault-determined-in-google-ai-overview-lawsuits-175",
  "mainEntity": [
    {
      "@type": "Question",
      "name": "How is fault determined in Google AI Overview lawsuits?",
      "acceptedAnswer": {
        "@type": "Answer",
        "text": "Section 230 usually absolves; negligence secondary.",
        "description": "Courts assess Section 230 first, then negligence if pierced.[2][5] Key factors: Platform immunity; gross negligence rare. Google rarely at fault."
      }
    }
  ]
}