{
  "@context": "https://schema.org",
  "@type": "FAQPage",
  "name": "What mistakes to avoid after bad AI referral in Chicago?",
  "description": "Preserve evidence, stay silent, hire lawyer now in IL.",
  "url": "aiovisibility.com/faq/general-what-mistakes-to-avoid-after-bad-ai-referral-in-chicago-188",
  "mainEntity": [
    {
      "@type": "Question",
      "name": "What mistakes to avoid after bad AI referral in Chicago?",
      "acceptedAnswer": {
        "@type": "Answer",
        "text": "Preserve evidence, stay silent, hire lawyer now in IL.",
        "description": "Don't delete records, talk to insurers, or sign waivers hastily. Preserve all evidence. Key factors: (1) No firm contact without lawyer; (2) Timeline notes; (3) No social posts. Act within limits. Get independent advice fast."
      }
    }
  ]
}